grub_wiz/BackupMgr.py
grub_wiz/CannedConfig.py
grub_wiz/DistroVars.py
grub_wiz/GrubCfgParser.py
grub_wiz/GrubFile.py
grub_wiz/GrubWriter.py
grub_wiz/ParamDiscovery.py
grub_wiz/UserConfigDir.py
grub_wiz/WarnDB.py
grub_wiz/WizValidator.py
grub_wiz/__init__.py
grub_wiz/canned_config.yaml
grub_wiz/main.py
grub_wiz-0.8.19.dist-info/entry_points.txt
grub_wiz-0.8.19.dist-info/licenses/LICENSE
grub_wiz-0.8.19.dist-info/WHEEL
grub_wiz-0.8.19.dist-info/METADATA
grub_wiz-0.8.19.dist-info/RECORD
