Metadata-Version: 2.4
Name: grub-wiz
Version: 0.8.19
Summary: Grub config assistant
Author-email: Joe Defen <joedef@duck.com>
Requires-Python: >=3.8
Classifier: License :: OSI Approved :: MIT License
Classifier: Programming Language :: Python :: 3
Classifier: Programming Language :: Python :: 3.8
Classifier: Programming Language :: Python :: 3.9
Classifier: Programming Language :: Python :: 3.10
Classifier: Operating System :: POSIX :: Linux
Classifier: Topic :: Multimedia :: Video
License-File: LICENSE
Requires-Dist: ruamel.yaml>=0.18.17
Requires-Dist: console-window==1.3.2
Project-URL: Homepage, https://github.com/joedefen/grub-wiz
